me4/rtl/alu.v
`timescale 1ns/1ps

module alu(opA, opB, sel, res);
	input [7:0] opA, opB;
	input [2:0] sel;
	output reg [7:0] res;
	reg [7:0] res_temp;
	reg [7:0] opA_mag;
	reg [7:0] opB_mag;	
	reg temp;

	always @ (*) begin
		case (sel)
			3'b000: begin
				// magnitude for 2's complement
				opA_mag = (opA[7] == 1'b1) ? (~opA + 1) : opA;
				opB_mag = (opB[7] == 1'b1) ? (~opB + 1) : opB;
			end
			3'b001: begin
				// magnitude for 2's complement
				opA_mag = (opA[7] == 1'b1) ? (~opA + 1) : opA;
				opB_mag = (opB[7] == 1'b1) ? (~opB + 1) : opB;
			end
			3'b010: begin
				// magnitude for 1's complement
				opA_mag = (opA[7] == 1'b1) ? (~opA) : opA;
				opB_mag = (opB[7] == 1'b1) ? (~opB) : opB;
			end
			3'b011: begin
				// magnitude for 1's complement
				opA_mag = (opA[7] == 1'b1) ? (~opA) : opA;
				opB_mag = (opB[7] == 1'b1) ? (~opB) : opB;
			end
			3'b100: begin
				// magnitude for signed magnitude
				opA_mag = (opA[7] == 1'b1) ? {1'b0, opA[6:0]} : opA;
				opB_mag = (opB[7] == 1'b1) ? {1'b0, opB[6:0]} : opB;
			end
			3'b101: begin
				// magnitude for signed magnitude
				opA_mag = (opA[7] == 1'b1) ? {1'b0, opA[6:0]} : opA;
				opB_mag = (opB[7] == 1'b1) ? {1'b0, opB[6:0]} : opB;
			end
		endcase
	end

	always @ (*) begin
		case (sel)
			// 2's complement addition
			3'b000: begin
				if (opA[7] ^ opB[7]) begin
					if (opA_mag >= opB_mag) begin
						res_temp = opA_mag - opB_mag;
						res = (opA[7] == 1'b1) ? (~res_temp + 1) : res_temp;
					end else begin
						res_temp = opB_mag - opA_mag;
						res = (opB[7] == 1'b1) ? (~res_temp + 1) : res_temp;
					end

				end
				// if same signs, add 
				else begin
					res_temp = opA_mag + opB_mag;
					res = (opA[7] == 1'b1) ? (~res_temp + 1) : res_temp;
				end // end if
			end // end opt-case
			
			// 2's complement subtraction
			3'b001: begin
				// if same signs, subtract
				if (!(opA[7] ^ opB[7])) begin
					if (opA_mag >= opB_mag) begin
						res_temp = opA_mag - opB_mag;
						res = (opA[7] == 1'b1) ? (~res_temp + 1) : res_temp;
					end else begin
						res_temp = opB_mag - opA_mag;
						res = (opB[7] == 1'b0) ? (~res_temp + 1) : res_temp;
					end
				end 
				// if different signs, add
				else begin
					res_temp = opA_mag + opB_mag;
					res = (opA[7] == 1'b1) ? (~res_temp + 1) : res_temp;
				end // end if
			end	// end opt-case

			// 1's complement addition
			3'b010: begin
				// if different signs, subtract
				if (opA[7] ^ opB[7]) begin
					if (opA_mag >= opB_mag) begin
						res_temp = opA_mag - opB_mag;
						res = (opA[7] == 1'b1) ? (~res_temp) : res_temp;
					end else begin
						res_temp = opB_mag - opA_mag;
						res = (opB[7] == 1'b1) ? (~res_temp) : res_temp;
					end
				end
				// if same signs, add
				else begin
					res_temp = opA_mag + opB_mag;
					res = (opA[7] == 1'b1) ? (~res_temp) : res_temp;
				end
			end

			// 1's complement subtraction
			3'b011: begin
				// if same signs, subtract
				if (!(opA[7] ^ opB[7])) begin
					if (opA_mag >= opB_mag) begin
						res_temp = opA_mag - opB_mag;
						res = (opA[7] == 1'b1) ? (~res_temp) : res_temp;
					end else begin
						res_temp = opB_mag - opA_mag;
						res = (opB[7] == 1'b0) ? (~res_temp) : res_temp;
					end
				end
				// if different signs, add
				else begin
					res_temp = opA_mag + opB_mag;
					res = (opA[7] == 1'b1) ? (~res_temp) : res_temp;
				end
			end

			// sign-magnitude addition
			3'b100: begin
				// if different signs, subtract
				if (opA[7] ^ opB[7]) begin
					if (opA_mag >= opB_mag) begin
						res_temp = opA_mag - opB_mag;
						res = (opA[7] == 1'b1) ? {1'b1, res_temp[6:0]} : res_temp;
					end else begin
						res_temp = opB_mag - opA_mag;
						res = (opB[7] == 1'b1) ? {1'b1, res_temp[6:0]} : res_temp;
					end
				end
				// if same signs, add
				else begin
					res_temp = opA_mag + opB_mag;
					res = (opA[7] == 1'b1) ? {1'b1, res_temp[6:0]} : res_temp;
				end
			end

			// sign-magnitude subtraction
			3'b101: begin
				// if same signs, subtract
				if (!(opA[7] ^ opB[7])) begin
					if (opA_mag >= opB_mag) begin
						res_temp = opA_mag - opB_mag;
						res = (opA[7] == 1'b1) ? {1'b1, res_temp[6:0]} : res_temp;
					end else begin
						res_temp = opB_mag - opA_mag;
						// because of (-) sign in front of opB
						res = (opB[7] == 1'b0) ? {1'b1, res_temp[6:0]} : res_temp;
					end
				end
				// if different signs, add
				else begin
					res_temp = opA_mag + opB_mag;
					res = (opA[7] == 1'b1) ? {1'b1, res_temp[6:0]} : res_temp;
				end
			end

			3'b110: begin
				res = opA & opB;
			end

			3'b111: begin
				res = opA | opB;
			end
		endcase
		
	end
endmodule

me4/me4/sim/tb_alu.v
`timescale 1ns/1ps
module tb_alu;
	reg [7:0] opA;
	reg [7:0] opB;
	reg [2:0] sel;
	wire [7:0] res;

	alu A1(.opA(opA), .opB(opB), .sel(sel), .res(res));

	initial begin
		$dumpfile("out.vcd");
		$dumpvars;
		//$vcdplusfile("tb_alu.vpd");
    //$vcdpluson;
		//$sdf_annotate("../mapped/alu_mapped.sdf", A1);

		// 2's complement addition
		sel = 3'b000;
		opA = 8'hFD;
		opB = 8'hFC;
		#10
		opA = 3;
		opB = 5;
		#10
		opA = 3;
		opB = -5;

		// 2's complement subtraction
		#10
		sel = 3'b001;
		opA = 5;
		opB = 7;
		#10
		opA = 7;
		opB = 5;
		#10
		opA = -5;
		opB = -7;
		#10
		opA = -7;
		opB = -5;
		#10
		opA = -5;
		opB = 7;
		#10
		opA = 5;
		opB = -7;


		// 1's complement addition
		#10
		sel = 3'b010;
		// -3 + (-4) = -7
		opA = 8'hFC;
		opB = 8'hFB;
		#10
		// 7 + 3 = 10
		opA = 8'h07;
		opB = 8'h03;
		#10
		// 3 + (-4) = -1
		opA = 8'h03;
		opB = 8'hFB;
		#10
		// (-3) + 4 = 1
		opA = 8'hFC;
		opB = 8'h04;


		// 1's complement subtraction
		#10
		sel = 3'b011;
		// -3 - (-4) = 1
		opA = 8'hFC;
		opB = 8'hFB;
		#10
		// 7 - 3 = 4
		opA = 8'h07;
		opB = 8'h03;
		#10
		// 3 - (-4) = 7
		opA = 8'h03;
		opB = 8'hFB;
		#10
		// (-3) - 4 = -7
		opA = 8'hFC;
		opB = 8'h04;

		// sign-magnitude addition
		#10
		sel = 3'b100;
		// -3 + (-4) = -7
		opA = 8'h83;
		opB = 8'h84;
		#10
		// 7 + 3 = 10
		opA = 8'h07;
		opB = 8'h03;
		#10
		// 3 + (-4) = -1
		opA = 8'h03;
		opB = 8'h84;
		#10
		// (-3) + 4 = 1
		opA = 8'h83;
		opB = 8'h04;

		// sign-magnitude subtraction
		#10
		sel = 3'b101;
		// -3 - (-4) = 1
		opA = 8'h83;
		opB = 8'h84;
		#10
		// 7 - 3 = 4
		opA = 8'h07;
		opB = 8'h03;
		#10
		// 3 - (-4) = 7
		opA = 8'h03;
		opB = 8'h84;
		#10
		// (-3) - 4 = -7
		opA = 8'h83;
		opB = 8'h04;

		// and operation
		#10
		sel = 3'b110;

		opA = 8'h83;
		opB = 8'h84;
		#10

		opA = 8'h07;
		opB = 8'h03;
		#10

		opA = 8'h03;
		opB = 8'h84;
		#10

		opA = 8'h83;
		opB = 8'h04;

		// or operation
		#10
		sel = 3'b111;

		opA = 8'h83;
		opB = 8'h84;
		#10

		opA = 8'h07;
		opB = 8'h03;
		#10

		opA = 8'h03;
		opB = 8'h84;
		#10

		opA = 8'h83;
		opB = 8'h04;

		#10
		$finish;
	end
endmodule

me4/out.vcd
$date
	Tue Sep 13 11:59:42 2016
$end
$version
	Icarus Verilog
$end
$timescale
	1ps
$end
$scope module tb_alu $end
$var wire 8 ! res [7:0] $end
$var reg 8 " opA [7:0] $end
$var reg 8 # opB [7:0] $end
$var reg 3 $ sel [2:0] $end
$scope module A1 $end
$var wire 8 % opA [7:0] $end
$var wire 8 & opB [7:0] $end
$var wire 3 ' sel [2:0] $end
$var reg 8 ( opA_mag [7:0] $end
$var reg 8 ) opB_mag [7:0] $end
$var reg 8 * res [7:0] $end
$var reg 8 + res_temp [7:0] $end
$upscope $end
$upscope $end
$enddefinitions $end
#0
$dumpvars
b111 +
b11111001 *
b100 )
b11 (
b0 '
b11111100 &
b11111101 %
b0 $
b11111100 #
b11111101 "
b11111001 !
$end
#10000
b1000 !
b1000 *
b1000 +
b101 )
b101 #
b101 &
b11 "
b11 %
#20000
b11111110 !
b11111110 *
b10 +
b11111011 #
b11111011 &
#30000
b111 )
b101 (
b111 #
b111 &
b101 "
b101 %
b1 $
b1 '
#40000
b10 !
b10 *
b101 )
b111 (
b101 #
b101 &
b111 "
b111 %
#50000
b111 )
b101 (
b11111001 #
b11111001 &
b11111011 "
b11111011 %
#60000
b11111110 !
b11111110 *
b101 )
b111 (
b11111011 #
b11111011 &
b11111001 "
b11111001 %
#70000
b11110100 !
b11110100 *
b1100 +
b111 )
b101 (
b111 #
b111 &
b11111011 "
b11111011 %
#80000
b1100 !
b1100 *
b11111001 #
b11111001 &
b101 "
b101 %
#90000
b11111000 !
b11111000 *
b111 +
b100 )
b11 (
b11111011 #
b11111011 &
b11111100 "
b11111100 %
b10 $
b10 '
#100000
b1010 !
b1010 *
b1010 +
b11 )
b111 (
b11 #
b11 &
b111 "
b111 %
#110000
b11111110 !
b11111110 *
b1 +
b100 )
b11 (
b11111011 #
b11111011 &
b11 "
b11 %
#120000
b1 !
b1 *
b100 #
b100 &
b11111100 "
b11111100 %
#130000
b11111011 #
b11111011 &
b11 $
b11 '
#140000
b100 !
b100 *
b100 +
b11 )
b111 (
b11 #
b11 &
b111 "
b111 %
#150000
b111 !
b111 *
b111 +
b100 )
b11 (
b11111011 #
b11111011 &
b11 "
b11 %
#160000
b11111000 !
b11111000 *
b100 #
b100 &
b11111100 "
b11111100 %
#170000
b10000111 !
b10000111 *
b10000100 #
b10000100 &
b10000011 "
b10000011 %
b100 $
b100 '
#180000
b1010 !
b1010 *
b1010 +
b11 )
b111 (
b11 #
b11 &
b111 "
b111 %
#190000
b10000001 !
b10000001 *
b1 +
b100 )
b11 (
b10000100 #
b10000100 &
b11 "
b11 %
#200000
b1 !
b1 *
b100 #
b100 &
b10000011 "
b10000011 %
#210000
b10000100 #
b10000100 &
b101 $
b101 '
#220000
b100 !
b100 *
b100 +
b11 )
b111 (
b11 #
b11 &
b111 "
b111 %
#230000
b111 !
b111 *
b111 +
b100 )
b11 (
b10000100 #
b10000100 &
b11 "
b11 %
#240000
b10000111 !
b10000111 *
b100 #
b100 &
b10000011 "
b10000011 %
#250000
b10000000 !
b10000000 *
b10000100 #
b10000100 &
b110 $
b110 '
#260000
b11 !
b11 *
b11 #
b11 &
b111 "
b111 %
#270000
b0 !
b0 *
b10000100 #
b10000100 &
b11 "
b11 %
#280000
b100 #
b100 &
b10000011 "
b10000011 %
#290000
b10000111 !
b10000111 *
b10000100 #
b10000100 &
b111 $
b111 '
#300000
b111 !
b111 *
b11 #
b11 &
b111 "
b111 %
#310000
b10000111 !
b10000111 *
b10000100 #
b10000100 &
b11 "
b11 %
#320000
b100 #
b100 &
b10000011 "
b10000011 %
